unprint/__init__.py
unprint-0.0.12.dist-info/METADATA
unprint-0.0.12.dist-info/WHEEL
unprint-0.0.12.dist-info/licenses/LICENSE
unprint-0.0.12.dist-info/RECORD
