Metadata-Version: 2.4
Name: unprint
Version: 0.0.12
Summary: A simple package to unprint stuff in terminal
Project-URL: Homepage, https://github.com/zlliu246/unprint
Project-URL: Issues, https://github.com/zlliu246/unprint/issues
Author-email: Liu Zuo Lin <zlliu246@gmail.com>
License-File: LICENSE
Classifier: License :: OSI Approved :: MIT License
Classifier: Operating System :: OS Independent
Classifier: Programming Language :: Python :: 3
Requires-Python: >=3.8
